nlpboss/__init__.py
nlpboss/callback.py
nlpboss-1.0.0.dist-info/METADATA
nlpboss-1.0.0.dist-info/WHEEL
nlpboss-1.0.0.dist-info/top_level.txt
nlpboss-1.0.0.dist-info/RECORD
