Metadata-Version: 2.1
Name: nlpboss
Version: 1.0.0
Summary: a callback<send train-info to email> for HuggingFace's Transformers Trainer
Home-page: https://github.com/yuanzhoulvpi2017/nlpboss
Author: yuanzhoulvpi2017
Author-email: 1582034172@qq.com
License: BSD License
Platform: all
Classifier: Intended Audience :: Developers
Classifier: Operating System :: OS Independent
Classifier: Natural Language :: Chinese (Simplified)
Classifier: Programming Language :: Python
Classifier: Programming Language :: Python :: 3.7
Classifier: Programming Language :: Python :: 3.8
Classifier: Programming Language :: Python :: 3.9
Classifier: Programming Language :: Python :: 3.10
Classifier: Topic :: Software Development :: Libraries
Requires-Dist: pandas
Requires-Dist: transformers
